saltext/test_salt_winrepo/__init__.py
saltext/test_salt_winrepo/version.py
saltext/test_salt_winrepo/modules/__init__.py
saltext/test_salt_winrepo/modules/test_salt_winrepo_mod.py
saltext_test_salt_winrepo-0.1.1.dist-info/LICENSE
saltext_test_salt_winrepo-0.1.1.dist-info/METADATA
saltext_test_salt_winrepo-0.1.1.dist-info/NOTICE
saltext_test_salt_winrepo-0.1.1.dist-info/WHEEL
saltext_test_salt_winrepo-0.1.1.dist-info/entry_points.txt
saltext_test_salt_winrepo-0.1.1.dist-info/top_level.txt
saltext_test_salt_winrepo-0.1.1.dist-info/RECORD
