Metadata-Version: 2.2
Name: saltext.test-salt-winrepo
Version: 0.1.1
Summary: Salt Extension for testing Salt Winrepo
Author-email: Dafydd Jones <4195158+dafyddj@users.noreply.github.com>
License: Apache Software License
Project-URL: Homepage, https://github.com/dafyddj/saltext-test-salt-winrepo
Project-URL: Source, https://github.com/dafyddj/saltext-test-salt-winrepo
Project-URL: Tracker, https://github.com/dafyddj/saltext-test-salt-winrepo/issues
Keywords: salt-extension
Platform: any
Classifier: Programming Language :: Python
Classifier: Programming Language :: Cython
Classifier: Programming Language :: Python :: 3
Classifier: Programming Language :: Python :: 3 :: Only
Classifier: Programming Language :: Python :: 3.10
Classifier: Development Status :: 4 - Beta
Classifier: Intended Audience :: Developers
Classifier: License :: OSI Approved :: Apache Software License
Requires-Python: >=3.10
License-File: LICENSE
License-File: NOTICE
Requires-Dist: salt>=3006
Provides-Extra: changelog
Requires-Dist: towncrier==24.8.0; extra == "changelog"
Provides-Extra: dev
Requires-Dist: nox[uv]>=2024.3; extra == "dev"
Requires-Dist: pre-commit>=2.21.0; extra == "dev"
Provides-Extra: dev-extra
Requires-Dist: black==25.1.0; extra == "dev-extra"
Requires-Dist: isort==6.0.1; extra == "dev-extra"
Requires-Dist: coverage==7.7.1; extra == "dev-extra"
Provides-Extra: docs
Requires-Dist: sphinx; extra == "docs"
Requires-Dist: sphinx-prompt; extra == "docs"
Requires-Dist: sphinxcontrib-spelling; extra == "docs"
Requires-Dist: sphinx-copybutton; extra == "docs"
Requires-Dist: towncrier==24.8.0; extra == "docs"
Requires-Dist: sphinxcontrib-towncrier; extra == "docs"
Requires-Dist: myst_parser; extra == "docs"
Requires-Dist: furo; extra == "docs"
Requires-Dist: sphinx-inline-tabs; extra == "docs"
Provides-Extra: docsauto
Requires-Dist: sphinx-autobuild; extra == "docsauto"
Provides-Extra: lint
Requires-Dist: pylint==3.3.5; extra == "lint"
Provides-Extra: tests
Requires-Dist: pytest>=7.2.0; extra == "tests"
Requires-Dist: pytest-salt-factories>=1.0.0; extra == "tests"
Requires-Dist: pytest-instafail; extra == "tests"
